[
  {
    "ReleaseNo": "",
    "automationTool": "Provar",
    "duration": "24.918",
    "environment": "CommQA",
    "execError": "_null_",
    "priority": "1",
    "productTeam": "",
    "testCaseResult": "Passed",
    "testEndTime": "2023-05-10 10:40:35.965",
    "testError": "_null_",
    "testName": "CreateAccountSMBwithNonRequiredFields ",
    "testOutCome": "successful",
    "testPath": "tests/Functional/SF-API/Account/CreateAccountsFromDataSheet.testcase",
    "testScriptName": "CreateAccountsFromDataSheet.testcase",
    "testStartTime": "2023-05-10 10:40:11.047"
  },
  {
    "ReleaseNo": "",
    "automationTool": "Provar",
    "duration": "9.327",
    "environment": "CommQA",
    "execError": "_null_",
    "priority": "1",
    "productTeam": "",
    "testCaseResult": "Passed",
    "testEndTime": "2023-05-10 10:40:47.771",
    "testError": "_null_",
    "testName": "CreateAccountCORPwithNonRequiredFields ",
    "testOutCome": "successful",
    "testPath": "tests/Functional/SF-API/Account/CreateAccountsFromDataSheet.testcase",
    "testScriptName": "CreateAccountsFromDataSheet.testcase",
    "testStartTime": "2023-05-10 10:40:38.444"
  },
  {
    "ReleaseNo": "",
    "automationTool": "Provar",
    "duration": "4.238",
    "environment": "CommQA",
    "execError": "_null_",
    "priority": "1",
    "productTeam": "",
    "testCaseResult": "Passed",
    "testEndTime": "2023-05-10 10:40:52.616",
    "testError": "_null_",
    "testName": "CreateAccountHCwithNonRequiredFields ",
    "testOutCome": "successful",
    "testPath": "tests/Functional/SF-API/Account/CreateAccountsFromDataSheet.testcase",
    "testScriptName": "CreateAccountsFromDataSheet.testcase",
    "testStartTime": "2023-05-10 10:40:48.378"
  },
  {
    "ReleaseNo": "",
    "automationTool": "Provar",
    "duration": "3.007",
    "environment": "CommQA",
    "execError": "_Warning: Nashorn engine is planned to be removed from a future JDK release,Failed to create Object.  Error Messages: bad value for restricted picklist field: 01,Failed to delete Object.  Error Messages: entity is deleted]_",
    "priority": "1",
    "productTeam": "",
    "testCaseResult": "Failed",
    "testEndTime": "2023-05-10 10:40:56.134",
    "testError": "_Warning: Nashorn engine is planned to be removed from a future JDK release,Failed to create Object.  Error Messages: bad value for restricted picklist field: 01,Failed to delete Object.  Error Messages: entity is deleted]_",
    "testName": "CreateAccountHEwithNonRequiredFields ",
    "testOutCome": "failed",
    "testPath": "tests/Functional/SF-API/Account/CreateAccountsFromDataSheet.testcase",
    "testScriptName": "CreateAccountsFromDataSheet.testcase",
    "testStartTime": "2023-05-10 10:40:53.127"
  },
  {
    "ReleaseNo": "",
    "automationTool": "Provar",
    "duration": "4.1",
    "environment": "CommQA",
    "execError": "_null_",
    "priority": "1",
    "productTeam": "",
    "testCaseResult": "Passed",
    "testEndTime": "2023-05-10 10:41:00.862",
    "testError": "_null_",
    "testName": "CreateAccountK12withNonRequiredFields ",
    "testOutCome": "failed",
    "testPath": "tests/Functional/SF-API/Account/CreateAccountsFromDataSheet.testcase",
    "testScriptName": "CreateAccountsFromDataSheet.testcase",
    "testStartTime": "2023-05-10 10:40:56.762"
  },
  {
    "ReleaseNo": "",
    "automationTool": "Provar",
    "duration": "3.945",
    "environment": "CommQA",
    "execError": "_null_",
    "priority": "1",
    "productTeam": "",
    "testCaseResult": "Passed",
    "testEndTime": "2023-05-10 10:41:05.375",
    "testError": "_null_",
    "testName": "CreateAccountwithSMBRequiredFields ",
    "testOutCome": "failed",
    "testPath": "tests/Functional/SF-API/Account/CreateAccountsFromDataSheet.testcase",
    "testScriptName": "CreateAccountsFromDataSheet.testcase",
    "testStartTime": "2023-05-10 10:41:01.43"
  },
  {
    "ReleaseNo": "",
    "automationTool": "Provar",
    "duration": "3.83",
    "environment": "CommQA",
    "execError": "_null_",
    "priority": "1",
    "productTeam": "",
    "testCaseResult": "Passed",
    "testEndTime": "2023-05-10 10:41:09.717",
    "testError": "_null_",
    "testName": "CreateAccountCORPwithRequiredFields ",
    "testOutCome": "failed",
    "testPath": "tests/Functional/SF-API/Account/CreateAccountsFromDataSheet.testcase",
    "testScriptName": "CreateAccountsFromDataSheet.testcase",
    "testStartTime": "2023-05-10 10:41:05.887"
  },
  {
    "ReleaseNo": "",
    "automationTool": "Provar",
    "duration": "4.069",
    "environment": "CommQA",
    "execError": "_null_",
    "priority": "1",
    "productTeam": "",
    "testCaseResult": "Passed",
    "testEndTime": "2023-05-10 10:41:14.285",
    "testError": "_null_",
    "testName": "CreateAccountHCwithRequiredFields ",
    "testOutCome": "failed",
    "testPath": "tests/Functional/SF-API/Account/CreateAccountsFromDataSheet.testcase",
    "testScriptName": "CreateAccountsFromDataSheet.testcase",
    "testStartTime": "2023-05-10 10:41:10.216"
  },
  {
    "ReleaseNo": "",
    "automationTool": "Provar",
    "duration": "4.254",
    "environment": "CommQA",
    "execError": "_null_",
    "priority": "1",
    "productTeam": "",
    "testCaseResult": "Passed",
    "testEndTime": "2023-05-10 10:41:19.235",
    "testError": "_null_",
    "testName": "CreateAccountHEwithRequiredFields ",
    "testOutCome": "failed",
    "testPath": "tests/Functional/SF-API/Account/CreateAccountsFromDataSheet.testcase",
    "testScriptName": "CreateAccountsFromDataSheet.testcase",
    "testStartTime": "2023-05-10 10:41:14.981"
  },
  {
    "ReleaseNo": "",
    "automationTool": "Provar",
    "duration": "3.744",
    "environment": "CommQA",
    "execError": "_null_",
    "priority": "1",
    "productTeam": "",
    "testCaseResult": "Passed",
    "testEndTime": "2023-05-10 10:41:23.464",
    "testError": "_null_",
    "testName": "CreateAccountK12withRequiredFields ",
    "testOutCome": "failed",
    "testPath": "tests/Functional/SF-API/Account/CreateAccountsFromDataSheet.testcase",
    "testScriptName": "CreateAccountsFromDataSheet.testcase",
    "testStartTime": "2023-05-10 10:41:19.72"
  }
]